artemis_client/__init__.py
artemis_client-0.1.0.dist-info/METADATA
artemis_client-0.1.0.dist-info/WHEEL
artemis_client-0.1.0.dist-info/top_level.txt
artemis_client-0.1.0.dist-info/RECORD
